py_spm/__init__.py
py_spm/_channel.py
py_spm/_data.py
py_spm/_event.py
py_spm/_meeg.py
py_spm/_trial.py
py_spm/skeleton.py
py_spm/utils.py
py_spm-0.0.3.dist-info/AUTHORS.rst
py_spm-0.0.3.dist-info/LICENSE.txt
py_spm-0.0.3.dist-info/METADATA
py_spm-0.0.3.dist-info/WHEEL
py_spm-0.0.3.dist-info/top_level.txt
py_spm-0.0.3.dist-info/RECORD
